{"cameraMode":{"drawMode":0,"name":"Shaded","section":"Shading Mode"},"sceneLighting":true,"audioPlay":false,"sceneViewState":{"showFog":true,"showMaterialUpdate":false,"showSkybox":true,"showFlares":true,"showImageEffects":true,"showParticleSystems":true},"in2DMode":false,"pivot":{"x":-4.080960273742676,"y":0.9443998336791992,"z":2.1909894943237306},"rotation":{"x":0.1532934308052063,"y":-0.7666367292404175,"z":0.19886988401412965,"w":0.590957522392273},"size":2.773824453353882,"orthographic":false}